{
  "minecraft:recipes/misc/charcoal": {
    "criteria": {
      "has_log": "2021-05-03 15:59:21 -0400"
    },
    "done": true
  },
  "minecraft:recipes/building_blocks/oak_planks": {
    "criteria": {
      "has_logs": "2021-05-03 16:02:40 -0400"
    },
    "done": true
  },
  "minecraft:recipes/transportation/dark_oak_boat": {
    "criteria": {
      "in_water": "2021-05-03 16:01:29 -0400"
    },
    "done": true
  },
  "minecraft:recipes/transportation/birch_boat": {
    "criteria": {
      "in_water": "2021-05-03 16:01:29 -0400"
    },
    "done": true
  },
  "minecraft:recipes/building_blocks/dark_oak_planks": {
    "criteria": {
      "has_log": "2021-05-03 15:59:21 -0400"
    },
    "done": true
  },
  "minecraft:recipes/food/cake": {
    "criteria": {
      "has_egg": "2021-05-03 16:17:05 -0400"
    },
    "done": true
  },
  "minecraft:recipes/misc/magenta_dye_from_lilac": {
    "criteria": {
      "has_double_plant": "2021-05-03 16:02:56 -0400"
    },
    "done": true
  },
  "minecraft:recipes/building_blocks/oak_wood": {
    "criteria": {
      "has_log": "2021-05-03 16:02:40 -0400"
    },
    "done": true
  },
  "minecraft:recipes/transportation/acacia_boat": {
    "criteria": {
      "in_water": "2021-05-03 16:01:29 -0400"
    },
    "done": true
  },
  "minecraft:recipes/building_blocks/birch_wood": {
    "criteria": {
      "has_log": "2021-05-03 16:01:45 -0400"
    },
    "done": true
  },
  "minecraft:recipes/transportation/oak_boat": {
    "criteria": {
      "in_water": "2021-05-03 16:01:29 -0400"
    },
    "done": true
  },
  "minecraft:recipes/building_blocks/dark_oak_wood": {
    "criteria": {
      "has_log": "2021-05-03 15:59:21 -0400"
    },
    "done": true
  },
  "minecraft:adventure/root": {
    "criteria": {
      "killed_by_something": "2021-05-03 16:12:19 -0400"
    },
    "done": true
  },
  "minecraft:recipes/transportation/jungle_boat": {
    "criteria": {
      "in_water": "2021-05-03 16:01:29 -0400"
    },
    "done": true
  },
  "minecraft:recipes/transportation/spruce_boat": {
    "criteria": {
      "in_water": "2021-05-03 16:01:29 -0400"
    },
    "done": true
  },
  "minecraft:adventure/adventuring_time": {
    "criteria": {
      "minecraft:warm_ocean": "2021-05-03 16:14:16 -0400",
      "minecraft:beach": "2021-05-03 16:02:28 -0400",
      "minecraft:dark_forest": "2021-05-03 16:01:31 -0400",
      "minecraft:river": "2021-05-03 16:13:52 -0400",
      "minecraft:lukewarm_ocean": "2021-05-03 16:13:46 -0400",
      "minecraft:plains": "2021-05-03 15:59:05 -0400"
    },
    "done": false
  },
  "minecraft:recipes/building_blocks/birch_planks": {
    "criteria": {
      "has_logs": "2021-05-03 16:01:45 -0400"
    },
    "done": true
  },
  "DataVersion": 2586
}